dpd_uploader/Uploader.py
dpd_uploader/__init__.py
dpd_uploader/_imports_.py
dpd_uploader/dpd_uploader.min.js
dpd_uploader/dpd_uploader.min.js.map
dpd_uploader/metadata.json
dpd_uploader/package-info.json
dpd_uploader-2.1.1.dist-info/LICENSE
dpd_uploader-2.1.1.dist-info/METADATA
dpd_uploader-2.1.1.dist-info/WHEEL
dpd_uploader-2.1.1.dist-info/top_level.txt
dpd_uploader-2.1.1.dist-info/RECORD
