Metadata-Version: 2.1
Name: dpd-uploader
Version: 2.1.1
Summary: Django Plotly Dash Uploader Component for Large Files using Resumablejs
Home-page: UNKNOWN
Author: Alexander Wolf <alex.r.wolf22@gmail.com>
Author-email: UNKNOWN
License: MIT
Platform: UNKNOWN
Classifier: Framework :: Dash
